{
  "v": "5.7.4",
  "fr": 30,
  "ip": 0,
  "op": 120,
  "w": 200,
  "h": 200,
  "nm": "Dharma Ashvattha Inverted Tree",
  "ddd": 0,
  "assets": [],
  "layers": [
    {
      "ddd": 0, "ind": 1, "ty": 4, "nm": "Trunk",
      "sr": 1,
      "ks": {
        "o": { "a": 0, "k": 100 }, "r": { "a": 0, "k": 0 },
        "p": { "a": 0, "k": [100, 100, 0] },
        "a": { "a": 0, "k": [0, 0, 0] },
        "s": { "a": 0, "k": [100, 100, 100] }
      },
      "shapes": [
        {
          "ty": "gr",
          "it": [
            { "ty": "sh", "ks": { "a": 0, "k": { "i": [[0,0],[0,0],[0,0],[0,0],[0,0],[0,0],[0,0],[0,0],[0,0],[0,0],[0,0],[0,0]], "o": [[0,0],[0,0],[0,0],[0,0],[0,0],[0,0],[0,0],[0,0],[0,0],[0,0],[0,0],[0,0]], "v": [[-18,-22],[-21,-14],[-17,-5],[-22,4],[-18,13],[-20,22],[19,22],[22,13],[18,4],[23,-5],[19,-14],[17,-22]], "c": true } }, "nm": "TrunkOutline" },
            { "ty": "fl", "c": { "a": 0, "k": [0.486, 0.314, 0.149, 1] }, "o": { "a": 0, "k": 100 }, "nm": "TrunkFill" },
            { "ty": "st", "c": { "a": 0, "k": [0.250, 0.150, 0.075, 1] }, "o": { "a": 0, "k": 100 }, "w": { "a": 0, "k": 1.5 }, "lc": 2, "lj": 2, "nm": "TrunkStroke" },
            { "ty": "tr", "p": { "a": 0, "k": [0, 0] }, "a": { "a": 0, "k": [0, 0] }, "s": { "a": 0, "k": [100, 100] }, "r": { "a": 0, "k": 0 }, "o": { "a": 0, "k": 100 } }
          ],
          "nm": "TrunkOutlineGroup"
        },
        {
          "ty": "gr",
          "it": [
            { "ty": "sh", "ks": { "a": 0, "k": { "i": [[0,0],[2,-1],[-1,2]], "o": [[-2,1],[1,-2],[0,0]], "v": [[-8,-18],[-6,-2],[-10,15]], "c": false } }, "nm": "BarkCrack1" },
            { "ty": "st", "c": { "a": 0, "k": [0.250, 0.150, 0.075, 1] }, "o": { "a": 0, "k": 75 }, "w": { "a": 0, "k": 1.2 }, "lc": 2, "lj": 2, "nm": "BarkCrack1Stroke" },
            { "ty": "tr", "p": { "a": 0, "k": [0, 0] }, "a": { "a": 0, "k": [0, 0] }, "s": { "a": 0, "k": [100, 100] }, "r": { "a": 0, "k": 0 }, "o": { "a": 0, "k": 100 } }
          ],
          "nm": "BarkCrack1Group"
        },
        {
          "ty": "gr",
          "it": [
            { "ty": "sh", "ks": { "a": 0, "k": { "i": [[0,0],[-1,-2],[2,1]], "o": [[1,2],[-2,-1],[0,0]], "v": [[6,-15],[8,3],[3,18]], "c": false } }, "nm": "BarkCrack2" },
            { "ty": "st", "c": { "a": 0, "k": [0.250, 0.150, 0.075, 1] }, "o": { "a": 0, "k": 70 }, "w": { "a": 0, "k": 1 }, "lc": 2, "lj": 2, "nm": "BarkCrack2Stroke" },
            { "ty": "tr", "p": { "a": 0, "k": [0, 0] }, "a": { "a": 0, "k": [0, 0] }, "s": { "a": 0, "k": [100, 100] }, "r": { "a": 0, "k": 0 }, "o": { "a": 0, "k": 100 } }
          ],
          "nm": "BarkCrack2Group"
        }
      ],
      "ip": 0, "op": 120, "st": 0, "bm": 0
    },
    {
      "ddd": 0, "ind": 2, "ty": 4, "nm": "RootSystem",
      "sr": 1,
      "ks": {
        "o": { "a": 0, "k": 100 }, "r": { "a": 0, "k": 0 },
        "p": { "a": 0, "k": [0, 0, 0] },
        "a": { "a": 0, "k": [0, 0, 0] },
        "s": { "a": 0, "k": [100, 100, 100] }
      },
      "shapes": [
        { "ty": "gr", "it": [
          { "ty": "sh", "ks": { "a": 0, "k": { "i": [[0,0],[22,8]], "o": [[-14,-2],[0,0]], "v": [[78,88],[18,30]], "c": false } }, "nm": "R1M" },
          { "ty": "st", "c": { "a": 0, "k": [0.651, 0.475, 0.306, 1] }, "o": { "a": 0, "k": 100 }, "w": { "a": 0, "k": 3.4 }, "lc": 2, "lj": 2, "nm": "R1MS" },
          { "ty": "tr", "p": { "a": 0, "k": [0,0] }, "a": { "a": 0, "k": [0,0] }, "s": { "a": 0, "k": [100,100] }, "r": { "a": 0, "k": 0 }, "o": { "a": 0, "k": 100 } }
        ], "nm": "R1MainG" },
        { "ty": "gr", "it": [
          { "ty": "sh", "ks": { "a": 0, "k": { "i": [[0,0],[5,2]], "o": [[-4,-2],[0,0]], "v": [[63,71],[44,58]], "c": false } }, "nm": "R1S1" },
          { "ty": "st", "c": { "a": 0, "k": [0.620, 0.451, 0.290, 1] }, "o": { "a": 0, "k": 100 }, "w": { "a": 0, "k": 2.2 }, "lc": 2, "lj": 2, "nm": "R1S1S" },
          { "ty": "tr", "p": { "a": 0, "k": [0,0] }, "a": { "a": 0, "k": [0,0] }, "s": { "a": 0, "k": [100,100] }, "r": { "a": 0, "k": 0 }, "o": { "a": 0, "k": 100 } }
        ], "nm": "R1S1G" },
        { "ty": "gr", "it": [
          { "ty": "sh", "ks": { "a": 0, "k": { "i": [[0,0],[3,1]], "o": [[-2,-1],[0,0]], "v": [[56,66],[48,58]], "c": false } }, "nm": "R1S1a" },
          { "ty": "st", "c": { "a": 0, "k": [0.580, 0.420, 0.270, 1] }, "o": { "a": 0, "k": 90 }, "w": { "a": 0, "k": 1.5 }, "lc": 2, "lj": 2, "nm": "R1S1aS" },
          { "ty": "tr", "p": { "a": 0, "k": [0,0] }, "a": { "a": 0, "k": [0,0] }, "s": { "a": 0, "k": [100,100] }, "r": { "a": 0, "k": 0 }, "o": { "a": 0, "k": 100 } }
        ], "nm": "R1S1aG" },
        { "ty": "gr", "it": [
          { "ty": "sh", "ks": { "a": 0, "k": { "i": [[0,0],[-2,2]], "o": [[2,-2],[0,0]], "v": [[58,64],[64,58]], "c": false } }, "nm": "R1S1b" },
          { "ty": "st", "c": { "a": 0, "k": [0.580, 0.420, 0.270, 1] }, "o": { "a": 0, "k": 90 }, "w": { "a": 0, "k": 1.4 }, "lc": 2, "lj": 2, "nm": "R1S1bS" },
          { "ty": "tr", "p": { "a": 0, "k": [0,0] }, "a": { "a": 0, "k": [0,0] }, "s": { "a": 0, "k": [100,100] }, "r": { "a": 0, "k": 0 }, "o": { "a": 0, "k": 100 } }
        ], "nm": "R1S1bG" },
        { "ty": "gr", "it": [
          { "ty": "sh", "ks": { "a": 0, "k": { "i": [[0,0],[4,1]], "o": [[-3,-1],[0,0]], "v": [[42,52],[30,46]], "c": false } }, "nm": "R1S2" },
          { "ty": "st", "c": { "a": 0, "k": [0.620, 0.451, 0.290, 1] }, "o": { "a": 0, "k": 100 }, "w": { "a": 0, "k": 2 }, "lc": 2, "lj": 2, "nm": "R1S2S" },
          { "ty": "tr", "p": { "a": 0, "k": [0,0] }, "a": { "a": 0, "k": [0,0] }, "s": { "a": 0, "k": [100,100] }, "r": { "a": 0, "k": 0 }, "o": { "a": 0, "k": 100 } }
        ], "nm": "R1S2G" },
        { "ty": "gr", "it": [
          { "ty": "sh", "ks": { "a": 0, "k": { "i": [[0,0],[2,0]], "o": [[-2,0],[0,0]], "v": [[37,49],[28,42]], "c": false } }, "nm": "R1S2a" },
          { "ty": "st", "c": { "a": 0, "k": [0.580, 0.420, 0.270, 1] }, "o": { "a": 0, "k": 90 }, "w": { "a": 0, "k": 1.4 }, "lc": 2, "lj": 2, "nm": "R1S2aS" },
          { "ty": "tr", "p": { "a": 0, "k": [0,0] }, "a": { "a": 0, "k": [0,0] }, "s": { "a": 0, "k": [100,100] }, "r": { "a": 0, "k": 0 }, "o": { "a": 0, "k": 100 } }
        ], "nm": "R1S2aG" },
        { "ty": "gr", "it": [
          { "ty": "sh", "ks": { "a": 0, "k": { "i": [[0,0],[0,0]], "o": [[0,0],[0,0]], "v": [[18,30],[10,24]], "c": false } }, "nm": "R1T1" },
          { "ty": "st", "c": { "a": 0, "k": [0.580, 0.420, 0.270, 1] }, "o": { "a": 0, "k": 90 }, "w": { "a": 0, "k": 1.3 }, "lc": 2, "lj": 2, "nm": "R1T1S" },
          { "ty": "tr", "p": { "a": 0, "k": [0,0] }, "a": { "a": 0, "k": [0,0] }, "s": { "a": 0, "k": [100,100] }, "r": { "a": 0, "k": 0 }, "o": { "a": 0, "k": 100 } }
        ], "nm": "R1T1G" },
        { "ty": "gr", "it": [
          { "ty": "sh", "ks": { "a": 0, "k": { "i": [[0,0],[0,0]], "o": [[0,0],[0,0]], "v": [[18,30],[14,18]], "c": false } }, "nm": "R1T2" },
          { "ty": "st", "c": { "a": 0, "k": [0.580, 0.420, 0.270, 1] }, "o": { "a": 0, "k": 85 }, "w": { "a": 0, "k": 1.1 }, "lc": 2, "lj": 2, "nm": "R1T2S" },
          { "ty": "tr", "p": { "a": 0, "k": [0,0] }, "a": { "a": 0, "k": [0,0] }, "s": { "a": 0, "k": [100,100] }, "r": { "a": 0, "k": 0 }, "o": { "a": 0, "k": 100 } }
        ], "nm": "R1T2G" },
        { "ty": "gr", "it": [
          { "ty": "sh", "ks": { "a": 0, "k": { "i": [[0,0],[8,14]], "o": [[-4,-8],[0,0]], "v": [[84,78],[50,8]], "c": false } }, "nm": "R2M" },
          { "ty": "st", "c": { "a": 0, "k": [0.651, 0.475, 0.306, 1] }, "o": { "a": 0, "k": 100 }, "w": { "a": 0, "k": 3.6 }, "lc": 2, "lj": 2, "nm": "R2MS" },
          { "ty": "tr", "p": { "a": 0, "k": [0,0] }, "a": { "a": 0, "k": [0,0] }, "s": { "a": 0, "k": [100,100] }, "r": { "a": 0, "k": 0 }, "o": { "a": 0, "k": 100 } }
        ], "nm": "R2MainG" },
        { "ty": "gr", "it": [
          { "ty": "sh", "ks": { "a": 0, "k": { "i": [[0,0],[3,3]], "o": [[-3,-3],[0,0]], "v": [[73,58],[60,42]], "c": false } }, "nm": "R2S1" },
          { "ty": "st", "c": { "a": 0, "k": [0.620, 0.451, 0.290, 1] }, "o": { "a": 0, "k": 100 }, "w": { "a": 0, "k": 2.2 }, "lc": 2, "lj": 2, "nm": "R2S1S" },
          { "ty": "tr", "p": { "a": 0, "k": [0,0] }, "a": { "a": 0, "k": [0,0] }, "s": { "a": 0, "k": [100,100] }, "r": { "a": 0, "k": 0 }, "o": { "a": 0, "k": 100 } }
        ], "nm": "R2S1G" },
        { "ty": "gr", "it": [
          { "ty": "sh", "ks": { "a": 0, "k": { "i": [[0,0],[1,2]], "o": [[-1,-2],[0,0]], "v": [[66,50],[58,40]], "c": false } }, "nm": "R2S1a" },
          { "ty": "st", "c": { "a": 0, "k": [0.580, 0.420, 0.270, 1] }, "o": { "a": 0, "k": 90 }, "w": { "a": 0, "k": 1.5 }, "lc": 2, "lj": 2, "nm": "R2S1aS" },
          { "ty": "tr", "p": { "a": 0, "k": [0,0] }, "a": { "a": 0, "k": [0,0] }, "s": { "a": 0, "k": [100,100] }, "r": { "a": 0, "k": 0 }, "o": { "a": 0, "k": 100 } }
        ], "nm": "R2S1aG" },
        { "ty": "gr", "it": [
          { "ty": "sh", "ks": { "a": 0, "k": { "i": [[0,0],[2,2]], "o": [[-2,-2],[0,0]], "v": [[62,30],[54,18]], "c": false } }, "nm": "R2S2" },
          { "ty": "st", "c": { "a": 0, "k": [0.620, 0.451, 0.290, 1] }, "o": { "a": 0, "k": 100 }, "w": { "a": 0, "k": 1.9 }, "lc": 2, "lj": 2, "nm": "R2S2S" },
          { "ty": "tr", "p": { "a": 0, "k": [0,0] }, "a": { "a": 0, "k": [0,0] }, "s": { "a": 0, "k": [100,100] }, "r": { "a": 0, "k": 0 }, "o": { "a": 0, "k": 100 } }
        ], "nm": "R2S2G" },
        { "ty": "gr", "it": [
          { "ty": "sh", "ks": { "a": 0, "k": { "i": [[0,0],[0,0]], "o": [[0,0],[0,0]], "v": [[50,8],[46,2]], "c": false } }, "nm": "R2T" },
          { "ty": "st", "c": { "a": 0, "k": [0.580, 0.420, 0.270, 1] }, "o": { "a": 0, "k": 85 }, "w": { "a": 0, "k": 1.2 }, "lc": 2, "lj": 2, "nm": "R2TS" },
          { "ty": "tr", "p": { "a": 0, "k": [0,0] }, "a": { "a": 0, "k": [0,0] }, "s": { "a": 0, "k": [100,100] }, "r": { "a": 0, "k": 0 }, "o": { "a": 0, "k": 100 } }
        ], "nm": "R2TG" },
        { "ty": "gr", "it": [
          { "ty": "sh", "ks": { "a": 0, "k": { "i": [[0,0],[4,5]], "o": [[-2,-3],[0,0]], "v": [[91,78],[78,36]], "c": false } }, "nm": "R3M" },
          { "ty": "st", "c": { "a": 0, "k": [0.651, 0.475, 0.306, 1] }, "o": { "a": 0, "k": 100 }, "w": { "a": 0, "k": 2.6 }, "lc": 2, "lj": 2, "nm": "R3MS" },
          { "ty": "tr", "p": { "a": 0, "k": [0,0] }, "a": { "a": 0, "k": [0,0] }, "s": { "a": 0, "k": [100,100] }, "r": { "a": 0, "k": 0 }, "o": { "a": 0, "k": 100 } }
        ], "nm": "R3MainG" },
        { "ty": "gr", "it": [
          { "ty": "sh", "ks": { "a": 0, "k": { "i": [[0,0],[2,1]], "o": [[-2,-1],[0,0]], "v": [[85,60],[76,52]], "c": false } }, "nm": "R3S1" },
          { "ty": "st", "c": { "a": 0, "k": [0.620, 0.451, 0.290, 1] }, "o": { "a": 0, "k": 100 }, "w": { "a": 0, "k": 1.8 }, "lc": 2, "lj": 2, "nm": "R3S1S" },
          { "ty": "tr", "p": { "a": 0, "k": [0,0] }, "a": { "a": 0, "k": [0,0] }, "s": { "a": 0, "k": [100,100] }, "r": { "a": 0, "k": 0 }, "o": { "a": 0, "k": 100 } }
        ], "nm": "R3S1G" },
        { "ty": "gr", "it": [
          { "ty": "sh", "ks": { "a": 0, "k": { "i": [[0,0],[1,1]], "o": [[-1,-1],[0,0]], "v": [[81,56],[74,50]], "c": false } }, "nm": "R3S1a" },
          { "ty": "st", "c": { "a": 0, "k": [0.580, 0.420, 0.270, 1] }, "o": { "a": 0, "k": 90 }, "w": { "a": 0, "k": 1.3 }, "lc": 2, "lj": 2, "nm": "R3S1aS" },
          { "ty": "tr", "p": { "a": 0, "k": [0,0] }, "a": { "a": 0, "k": [0,0] }, "s": { "a": 0, "k": [100,100] }, "r": { "a": 0, "k": 0 }, "o": { "a": 0, "k": 100 } }
        ], "nm": "R3S1aG" },
        { "ty": "gr", "it": [
          { "ty": "sh", "ks": { "a": 0, "k": { "i": [[0,0],[0,0]], "o": [[0,0],[0,0]], "v": [[78,36],[73,30]], "c": false } }, "nm": "R3T" },
          { "ty": "st", "c": { "a": 0, "k": [0.580, 0.420, 0.270, 1] }, "o": { "a": 0, "k": 85 }, "w": { "a": 0, "k": 1.2 }, "lc": 2, "lj": 2, "nm": "R3TS" },
          { "ty": "tr", "p": { "a": 0, "k": [0,0] }, "a": { "a": 0, "k": [0,0] }, "s": { "a": 0, "k": [100,100] }, "r": { "a": 0, "k": 0 }, "o": { "a": 0, "k": 100 } }
        ], "nm": "R3TG" },
        { "ty": "gr", "it": [
          { "ty": "sh", "ks": { "a": 0, "k": { "i": [[0,0],[-2,0]], "o": [[2,0],[0,0]], "v": [[97,78],[98,50]], "c": false } }, "nm": "R4M" },
          { "ty": "st", "c": { "a": 0, "k": [0.651, 0.475, 0.306, 1] }, "o": { "a": 0, "k": 100 }, "w": { "a": 0, "k": 2.4 }, "lc": 2, "lj": 2, "nm": "R4MS" },
          { "ty": "tr", "p": { "a": 0, "k": [0,0] }, "a": { "a": 0, "k": [0,0] }, "s": { "a": 0, "k": [100,100] }, "r": { "a": 0, "k": 0 }, "o": { "a": 0, "k": 100 } }
        ], "nm": "R4MainG" },
        { "ty": "gr", "it": [
          { "ty": "sh", "ks": { "a": 0, "k": { "i": [[0,0],[1,1]], "o": [[-1,-1],[0,0]], "v": [[98,68],[92,60]], "c": false } }, "nm": "R4S" },
          { "ty": "st", "c": { "a": 0, "k": [0.620, 0.451, 0.290, 1] }, "o": { "a": 0, "k": 100 }, "w": { "a": 0, "k": 1.7 }, "lc": 2, "lj": 2, "nm": "R4SS" },
          { "ty": "tr", "p": { "a": 0, "k": [0,0] }, "a": { "a": 0, "k": [0,0] }, "s": { "a": 0, "k": [100,100] }, "r": { "a": 0, "k": 0 }, "o": { "a": 0, "k": 100 } }
        ], "nm": "R4SG" },
        { "ty": "gr", "it": [
          { "ty": "sh", "ks": { "a": 0, "k": { "i": [[0,0],[0,14]], "o": [[0,-14],[0,0]], "v": [[100,78],[100,4]], "c": false } }, "nm": "R5M" },
          { "ty": "st", "c": { "a": 0, "k": [0.651, 0.475, 0.306, 1] }, "o": { "a": 0, "k": 100 }, "w": { "a": 0, "k": 3.8 }, "lc": 2, "lj": 2, "nm": "R5MS" },
          { "ty": "tr", "p": { "a": 0, "k": [0,0] }, "a": { "a": 0, "k": [0,0] }, "s": { "a": 0, "k": [100,100] }, "r": { "a": 0, "k": 0 }, "o": { "a": 0, "k": 100 } }
        ], "nm": "R5MainG" },
        { "ty": "gr", "it": [
          { "ty": "sh", "ks": { "a": 0, "k": { "i": [[0,0],[-3,0]], "o": [[3,0],[0,0]], "v": [[100,58],[86,48]], "c": false } }, "nm": "R5S1L" },
          { "ty": "st", "c": { "a": 0, "k": [0.620, 0.451, 0.290, 1] }, "o": { "a": 0, "k": 100 }, "w": { "a": 0, "k": 2 }, "lc": 2, "lj": 2, "nm": "R5S1LS" },
          { "ty": "tr", "p": { "a": 0, "k": [0,0] }, "a": { "a": 0, "k": [0,0] }, "s": { "a": 0, "k": [100,100] }, "r": { "a": 0, "k": 0 }, "o": { "a": 0, "k": 100 } }
        ], "nm": "R5S1LG" },
        { "ty": "gr", "it": [
          { "ty": "sh", "ks": { "a": 0, "k": { "i": [[0,0],[-2,0]], "o": [[2,0],[0,0]], "v": [[93,53],[84,46]], "c": false } }, "nm": "R5S1La" },
          { "ty": "st", "c": { "a": 0, "k": [0.580, 0.420, 0.270, 1] }, "o": { "a": 0, "k": 90 }, "w": { "a": 0, "k": 1.4 }, "lc": 2, "lj": 2, "nm": "R5S1LaS" },
          { "ty": "tr", "p": { "a": 0, "k": [0,0] }, "a": { "a": 0, "k": [0,0] }, "s": { "a": 0, "k": [100,100] }, "r": { "a": 0, "k": 0 }, "o": { "a": 0, "k": 100 } }
        ], "nm": "R5S1LaG" },
        { "ty": "gr", "it": [
          { "ty": "sh", "ks": { "a": 0, "k": { "i": [[0,0],[3,0]], "o": [[-3,0],[0,0]], "v": [[100,54],[114,44]], "c": false } }, "nm": "R5S1R" },
          { "ty": "st", "c": { "a": 0, "k": [0.620, 0.451, 0.290, 1] }, "o": { "a": 0, "k": 100 }, "w": { "a": 0, "k": 2 }, "lc": 2, "lj": 2, "nm": "R5S1RS" },
          { "ty": "tr", "p": { "a": 0, "k": [0,0] }, "a": { "a": 0, "k": [0,0] }, "s": { "a": 0, "k": [100,100] }, "r": { "a": 0, "k": 0 }, "o": { "a": 0, "k": 100 } }
        ], "nm": "R5S1RG" },
        { "ty": "gr", "it": [
          { "ty": "sh", "ks": { "a": 0, "k": { "i": [[0,0],[2,0]], "o": [[-2,0],[0,0]], "v": [[107,49],[116,42]], "c": false } }, "nm": "R5S1Ra" },
          { "ty": "st", "c": { "a": 0, "k": [0.580, 0.420, 0.270, 1] }, "o": { "a": 0, "k": 90 }, "w": { "a": 0, "k": 1.4 }, "lc": 2, "lj": 2, "nm": "R5S1RaS" },
          { "ty": "tr", "p": { "a": 0, "k": [0,0] }, "a": { "a": 0, "k": [0,0] }, "s": { "a": 0, "k": [100,100] }, "r": { "a": 0, "k": 0 }, "o": { "a": 0, "k": 100 } }
        ], "nm": "R5S1RaG" },
        { "ty": "gr", "it": [
          { "ty": "sh", "ks": { "a": 0, "k": { "i": [[0,0],[-1,1]], "o": [[1,-1],[0,0]], "v": [[100,28],[93,20]], "c": false } }, "nm": "R5S2L" },
          { "ty": "st", "c": { "a": 0, "k": [0.620, 0.451, 0.290, 1] }, "o": { "a": 0, "k": 100 }, "w": { "a": 0, "k": 1.7 }, "lc": 2, "lj": 2, "nm": "R5S2LS" },
          { "ty": "tr", "p": { "a": 0, "k": [0,0] }, "a": { "a": 0, "k": [0,0] }, "s": { "a": 0, "k": [100,100] }, "r": { "a": 0, "k": 0 }, "o": { "a": 0, "k": 100 } }
        ], "nm": "R5S2LG" },
        { "ty": "gr", "it": [
          { "ty": "sh", "ks": { "a": 0, "k": { "i": [[0,0],[1,1]], "o": [[-1,-1],[0,0]], "v": [[100,26],[107,20]], "c": false } }, "nm": "R5S2R" },
          { "ty": "st", "c": { "a": 0, "k": [0.620, 0.451, 0.290, 1] }, "o": { "a": 0, "k": 100 }, "w": { "a": 0, "k": 1.7 }, "lc": 2, "lj": 2, "nm": "R5S2RS" },
          { "ty": "tr", "p": { "a": 0, "k": [0,0] }, "a": { "a": 0, "k": [0,0] }, "s": { "a": 0, "k": [100,100] }, "r": { "a": 0, "k": 0 }, "o": { "a": 0, "k": 100 } }
        ], "nm": "R5S2RG" },
        { "ty": "gr", "it": [
          { "ty": "sh", "ks": { "a": 0, "k": { "i": [[0,0],[0,0]], "o": [[0,0],[0,0]], "v": [[100,4],[94,-1]], "c": false } }, "nm": "R5T1" },
          { "ty": "st", "c": { "a": 0, "k": [0.580, 0.420, 0.270, 1] }, "o": { "a": 0, "k": 85 }, "w": { "a": 0, "k": 1.2 }, "lc": 2, "lj": 2, "nm": "R5T1S" },
          { "ty": "tr", "p": { "a": 0, "k": [0,0] }, "a": { "a": 0, "k": [0,0] }, "s": { "a": 0, "k": [100,100] }, "r": { "a": 0, "k": 0 }, "o": { "a": 0, "k": 100 } }
        ], "nm": "R5T1G" },
        { "ty": "gr", "it": [
          { "ty": "sh", "ks": { "a": 0, "k": { "i": [[0,0],[0,0]], "o": [[0,0],[0,0]], "v": [[100,4],[106,-1]], "c": false } }, "nm": "R5T2" },
          { "ty": "st", "c": { "a": 0, "k": [0.580, 0.420, 0.270, 1] }, "o": { "a": 0, "k": 85 }, "w": { "a": 0, "k": 1.2 }, "lc": 2, "lj": 2, "nm": "R5T2S" },
          { "ty": "tr", "p": { "a": 0, "k": [0,0] }, "a": { "a": 0, "k": [0,0] }, "s": { "a": 0, "k": [100,100] }, "r": { "a": 0, "k": 0 }, "o": { "a": 0, "k": 100 } }
        ], "nm": "R5T2G" },
        { "ty": "gr", "it": [
          { "ty": "sh", "ks": { "a": 0, "k": { "i": [[0,0],[2,0]], "o": [[-2,0],[0,0]], "v": [[103,78],[104,54]], "c": false } }, "nm": "R6M" },
          { "ty": "st", "c": { "a": 0, "k": [0.651, 0.475, 0.306, 1] }, "o": { "a": 0, "k": 100 }, "w": { "a": 0, "k": 2.2 }, "lc": 2, "lj": 2, "nm": "R6MS" },
          { "ty": "tr", "p": { "a": 0, "k": [0,0] }, "a": { "a": 0, "k": [0,0] }, "s": { "a": 0, "k": [100,100] }, "r": { "a": 0, "k": 0 }, "o": { "a": 0, "k": 100 } }
        ], "nm": "R6MainG" },
        { "ty": "gr", "it": [
          { "ty": "sh", "ks": { "a": 0, "k": { "i": [[0,0],[-1,1]], "o": [[1,-1],[0,0]], "v": [[103,68],[110,62]], "c": false } }, "nm": "R6S" },
          { "ty": "st", "c": { "a": 0, "k": [0.620, 0.451, 0.290, 1] }, "o": { "a": 0, "k": 100 }, "w": { "a": 0, "k": 1.6 }, "lc": 2, "lj": 2, "nm": "R6SS" },
          { "ty": "tr", "p": { "a": 0, "k": [0,0] }, "a": { "a": 0, "k": [0,0] }, "s": { "a": 0, "k": [100,100] }, "r": { "a": 0, "k": 0 }, "o": { "a": 0, "k": 100 } }
        ], "nm": "R6SG" },
        { "ty": "gr", "it": [
          { "ty": "sh", "ks": { "a": 0, "k": { "i": [[0,0],[-4,5]], "o": [[2,-3],[0,0]], "v": [[109,78],[124,32]], "c": false } }, "nm": "R7M" },
          { "ty": "st", "c": { "a": 0, "k": [0.651, 0.475, 0.306, 1] }, "o": { "a": 0, "k": 100 }, "w": { "a": 0, "k": 2.6 }, "lc": 2, "lj": 2, "nm": "R7MS" },
          { "ty": "tr", "p": { "a": 0, "k": [0,0] }, "a": { "a": 0, "k": [0,0] }, "s": { "a": 0, "k": [100,100] }, "r": { "a": 0, "k": 0 }, "o": { "a": 0, "k": 100 } }
        ], "nm": "R7MainG" },
        { "ty": "gr", "it": [
          { "ty": "sh", "ks": { "a": 0, "k": { "i": [[0,0],[-2,1]], "o": [[2,-1],[0,0]], "v": [[115,60],[124,52]], "c": false } }, "nm": "R7S1" },
          { "ty": "st", "c": { "a": 0, "k": [0.620, 0.451, 0.290, 1] }, "o": { "a": 0, "k": 100 }, "w": { "a": 0, "k": 1.8 }, "lc": 2, "lj": 2, "nm": "R7S1S" },
          { "ty": "tr", "p": { "a": 0, "k": [0,0] }, "a": { "a": 0, "k": [0,0] }, "s": { "a": 0, "k": [100,100] }, "r": { "a": 0, "k": 0 }, "o": { "a": 0, "k": 100 } }
        ], "nm": "R7S1G" },
        { "ty": "gr", "it": [
          { "ty": "sh", "ks": { "a": 0, "k": { "i": [[0,0],[-1,1]], "o": [[1,-1],[0,0]], "v": [[119,57],[126,52]], "c": false } }, "nm": "R7S1a" },
          { "ty": "st", "c": { "a": 0, "k": [0.580, 0.420, 0.270, 1] }, "o": { "a": 0, "k": 90 }, "w": { "a": 0, "k": 1.3 }, "lc": 2, "lj": 2, "nm": "R7S1aS" },
          { "ty": "tr", "p": { "a": 0, "k": [0,0] }, "a": { "a": 0, "k": [0,0] }, "s": { "a": 0, "k": [100,100] }, "r": { "a": 0, "k": 0 }, "o": { "a": 0, "k": 100 } }
        ], "nm": "R7S1aG" },
        { "ty": "gr", "it": [
          { "ty": "sh", "ks": { "a": 0, "k": { "i": [[0,0],[0,0]], "o": [[0,0],[0,0]], "v": [[124,32],[130,26]], "c": false } }, "nm": "R7T" },
          { "ty": "st", "c": { "a": 0, "k": [0.580, 0.420, 0.270, 1] }, "o": { "a": 0, "k": 85 }, "w": { "a": 0, "k": 1.2 }, "lc": 2, "lj": 2, "nm": "R7TS" },
          { "ty": "tr", "p": { "a": 0, "k": [0,0] }, "a": { "a": 0, "k": [0,0] }, "s": { "a": 0, "k": [100,100] }, "r": { "a": 0, "k": 0 }, "o": { "a": 0, "k": 100 } }
        ], "nm": "R7TG" },
        { "ty": "gr", "it": [
          { "ty": "sh", "ks": { "a": 0, "k": { "i": [[0,0],[-8,14]], "o": [[4,-8],[0,0]], "v": [[116,78],[152,8]], "c": false } }, "nm": "R8M" },
          { "ty": "st", "c": { "a": 0, "k": [0.651, 0.475, 0.306, 1] }, "o": { "a": 0, "k": 100 }, "w": { "a": 0, "k": 3.6 }, "lc": 2, "lj": 2, "nm": "R8MS" },
          { "ty": "tr", "p": { "a": 0, "k": [0,0] }, "a": { "a": 0, "k": [0,0] }, "s": { "a": 0, "k": [100,100] }, "r": { "a": 0, "k": 0 }, "o": { "a": 0, "k": 100 } }
        ], "nm": "R8MainG" },
        { "ty": "gr", "it": [
          { "ty": "sh", "ks": { "a": 0, "k": { "i": [[0,0],[-3,3]], "o": [[3,-3],[0,0]], "v": [[127,58],[140,42]], "c": false } }, "nm": "R8S1" },
          { "ty": "st", "c": { "a": 0, "k": [0.620, 0.451, 0.290, 1] }, "o": { "a": 0, "k": 100 }, "w": { "a": 0, "k": 2.2 }, "lc": 2, "lj": 2, "nm": "R8S1S" },
          { "ty": "tr", "p": { "a": 0, "k": [0,0] }, "a": { "a": 0, "k": [0,0] }, "s": { "a": 0, "k": [100,100] }, "r": { "a": 0, "k": 0 }, "o": { "a": 0, "k": 100 } }
        ], "nm": "R8S1G" },
        { "ty": "gr", "it": [
          { "ty": "sh", "ks": { "a": 0, "k": { "i": [[0,0],[-1,2]], "o": [[1,-2],[0,0]], "v": [[134,50],[142,40]], "c": false } }, "nm": "R8S1a" },
          { "ty": "st", "c": { "a": 0, "k": [0.580, 0.420, 0.270, 1] }, "o": { "a": 0, "k": 90 }, "w": { "a": 0, "k": 1.5 }, "lc": 2, "lj": 2, "nm": "R8S1aS" },
          { "ty": "tr", "p": { "a": 0, "k": [0,0] }, "a": { "a": 0, "k": [0,0] }, "s": { "a": 0, "k": [100,100] }, "r": { "a": 0, "k": 0 }, "o": { "a": 0, "k": 100 } }
        ], "nm": "R8S1aG" },
        { "ty": "gr", "it": [
          { "ty": "sh", "ks": { "a": 0, "k": { "i": [[0,0],[-2,2]], "o": [[2,-2],[0,0]], "v": [[138,30],[146,18]], "c": false } }, "nm": "R8S2" },
          { "ty": "st", "c": { "a": 0, "k": [0.620, 0.451, 0.290, 1] }, "o": { "a": 0, "k": 100 }, "w": { "a": 0, "k": 1.9 }, "lc": 2, "lj": 2, "nm": "R8S2S" },
          { "ty": "tr", "p": { "a": 0, "k": [0,0] }, "a": { "a": 0, "k": [0,0] }, "s": { "a": 0, "k": [100,100] }, "r": { "a": 0, "k": 0 }, "o": { "a": 0, "k": 100 } }
        ], "nm": "R8S2G" },
        { "ty": "gr", "it": [
          { "ty": "sh", "ks": { "a": 0, "k": { "i": [[0,0],[0,0]], "o": [[0,0],[0,0]], "v": [[152,8],[156,2]], "c": false } }, "nm": "R8T" },
          { "ty": "st", "c": { "a": 0, "k": [0.580, 0.420, 0.270, 1] }, "o": { "a": 0, "k": 85 }, "w": { "a": 0, "k": 1.2 }, "lc": 2, "lj": 2, "nm": "R8TS" },
          { "ty": "tr", "p": { "a": 0, "k": [0,0] }, "a": { "a": 0, "k": [0,0] }, "s": { "a": 0, "k": [100,100] }, "r": { "a": 0, "k": 0 }, "o": { "a": 0, "k": 100 } }
        ], "nm": "R8TG" },
        { "ty": "gr", "it": [
          { "ty": "sh", "ks": { "a": 0, "k": { "i": [[0,0],[-22,8]], "o": [[14,-2],[0,0]], "v": [[122,88],[182,30]], "c": false } }, "nm": "R9M" },
          { "ty": "st", "c": { "a": 0, "k": [0.651, 0.475, 0.306, 1] }, "o": { "a": 0, "k": 100 }, "w": { "a": 0, "k": 3.4 }, "lc": 2, "lj": 2, "nm": "R9MS" },
          { "ty": "tr", "p": { "a": 0, "k": [0,0] }, "a": { "a": 0, "k": [0,0] }, "s": { "a": 0, "k": [100,100] }, "r": { "a": 0, "k": 0 }, "o": { "a": 0, "k": 100 } }
        ], "nm": "R9MainG" },
        { "ty": "gr", "it": [
          { "ty": "sh", "ks": { "a": 0, "k": { "i": [[0,0],[-5,2]], "o": [[4,-2],[0,0]], "v": [[137,71],[156,58]], "c": false } }, "nm": "R9S1" },
          { "ty": "st", "c": { "a": 0, "k": [0.620, 0.451, 0.290, 1] }, "o": { "a": 0, "k": 100 }, "w": { "a": 0, "k": 2.2 }, "lc": 2, "lj": 2, "nm": "R9S1S" },
          { "ty": "tr", "p": { "a": 0, "k": [0,0] }, "a": { "a": 0, "k": [0,0] }, "s": { "a": 0, "k": [100,100] }, "r": { "a": 0, "k": 0 }, "o": { "a": 0, "k": 100 } }
        ], "nm": "R9S1G" },
        { "ty": "gr", "it": [
          { "ty": "sh", "ks": { "a": 0, "k": { "i": [[0,0],[-3,1]], "o": [[2,-1],[0,0]], "v": [[144,66],[152,60]], "c": false } }, "nm": "R9S1a" },
          { "ty": "st", "c": { "a": 0, "k": [0.580, 0.420, 0.270, 1] }, "o": { "a": 0, "k": 90 }, "w": { "a": 0, "k": 1.5 }, "lc": 2, "lj": 2, "nm": "R9S1aS" },
          { "ty": "tr", "p": { "a": 0, "k": [0,0] }, "a": { "a": 0, "k": [0,0] }, "s": { "a": 0, "k": [100,100] }, "r": { "a": 0, "k": 0 }, "o": { "a": 0, "k": 100 } }
        ], "nm": "R9S1aG" },
        { "ty": "gr", "it": [
          { "ty": "sh", "ks": { "a": 0, "k": { "i": [[0,0],[2,-2]], "o": [[-2,2],[0,0]], "v": [[142,68],[136,58]], "c": false } }, "nm": "R9S1b" },
          { "ty": "st", "c": { "a": 0, "k": [0.580, 0.420, 0.270, 1] }, "o": { "a": 0, "k": 90 }, "w": { "a": 0, "k": 1.4 }, "lc": 2, "lj": 2, "nm": "R9S1bS" },
          { "ty": "tr", "p": { "a": 0, "k": [0,0] }, "a": { "a": 0, "k": [0,0] }, "s": { "a": 0, "k": [100,100] }, "r": { "a": 0, "k": 0 }, "o": { "a": 0, "k": 100 } }
        ], "nm": "R9S1bG" },
        { "ty": "gr", "it": [
          { "ty": "sh", "ks": { "a": 0, "k": { "i": [[0,0],[-3,2]], "o": [[3,-2],[0,0]], "v": [[160,52],[170,44]], "c": false } }, "nm": "R9S2" },
          { "ty": "st", "c": { "a": 0, "k": [0.620, 0.451, 0.290, 1] }, "o": { "a": 0, "k": 100 }, "w": { "a": 0, "k": 1.9 }, "lc": 2, "lj": 2, "nm": "R9S2S" },
          { "ty": "tr", "p": { "a": 0, "k": [0,0] }, "a": { "a": 0, "k": [0,0] }, "s": { "a": 0, "k": [100,100] }, "r": { "a": 0, "k": 0 }, "o": { "a": 0, "k": 100 } }
        ], "nm": "R9S2G" },
        { "ty": "gr", "it": [
          { "ty": "sh", "ks": { "a": 0, "k": { "i": [[0,0],[-2,1]], "o": [[2,-1],[0,0]], "v": [[165,48],[172,42]], "c": false } }, "nm": "R9S2a" },
          { "ty": "st", "c": { "a": 0, "k": [0.580, 0.420, 0.270, 1] }, "o": { "a": 0, "k": 90 }, "w": { "a": 0, "k": 1.4 }, "lc": 2, "lj": 2, "nm": "R9S2aS" },
          { "ty": "tr", "p": { "a": 0, "k": [0,0] }, "a": { "a": 0, "k": [0,0] }, "s": { "a": 0, "k": [100,100] }, "r": { "a": 0, "k": 0 }, "o": { "a": 0, "k": 100 } }
        ], "nm": "R9S2aG" },
        { "ty": "gr", "it": [
          { "ty": "sh", "ks": { "a": 0, "k": { "i": [[0,0],[0,0]], "o": [[0,0],[0,0]], "v": [[182,30],[190,22]], "c": false } }, "nm": "R9T1" },
          { "ty": "st", "c": { "a": 0, "k": [0.580, 0.420, 0.270, 1] }, "o": { "a": 0, "k": 90 }, "w": { "a": 0, "k": 1.3 }, "lc": 2, "lj": 2, "nm": "R9T1S" },
          { "ty": "tr", "p": { "a": 0, "k": [0,0] }, "a": { "a": 0, "k": [0,0] }, "s": { "a": 0, "k": [100,100] }, "r": { "a": 0, "k": 0 }, "o": { "a": 0, "k": 100 } }
        ], "nm": "R9T1G" },
        { "ty": "gr", "it": [
          { "ty": "sh", "ks": { "a": 0, "k": { "i": [[0,0],[0,0]], "o": [[0,0],[0,0]], "v": [[182,30],[186,18]], "c": false } }, "nm": "R9T2" },
          { "ty": "st", "c": { "a": 0, "k": [0.580, 0.420, 0.270, 1] }, "o": { "a": 0, "k": 85 }, "w": { "a": 0, "k": 1.1 }, "lc": 2, "lj": 2, "nm": "R9T2S" },
          { "ty": "tr", "p": { "a": 0, "k": [0,0] }, "a": { "a": 0, "k": [0,0] }, "s": { "a": 0, "k": [100,100] }, "r": { "a": 0, "k": 0 }, "o": { "a": 0, "k": 100 } }
        ], "nm": "R9T2G" }
      ],
      "ip": 0, "op": 120, "st": 0, "bm": 0
    },
    {
      "ddd": 0, "ind": 3, "ty": 4, "nm": "BranchSystem",
      "sr": 1,
      "ks": {
        "o": { "a": 0, "k": 100 }, "r": { "a": 0, "k": 0 },
        "p": { "a": 0, "k": [0, 0, 0] },
        "a": { "a": 0, "k": [0, 0, 0] },
        "s": { "a": 0, "k": [100, 100, 100] }
      },
      "shapes": [
        { "ty": "gr", "it": [
          { "ty": "sh", "ks": { "a": 0, "k": { "i": [[0,0],[22,-8]], "o": [[-14,3],[0,0]], "v": [[80,114],[22,162]], "c": false } }, "nm": "B1M" },
          { "ty": "st", "c": { "a": 0, "k": [0.486, 0.314, 0.149, 1] }, "o": { "a": 0, "k": 100 }, "w": { "a": 0, "k": 3.4 }, "lc": 2, "lj": 2, "nm": "B1MS" },
          { "ty": "tr", "p": { "a": 0, "k": [0,0] }, "a": { "a": 0, "k": [0,0] }, "s": { "a": 0, "k": [100,100] }, "r": { "a": 0, "k": 0 }, "o": { "a": 0, "k": 100 } }
        ], "nm": "B1MainG" },
        { "ty": "gr", "it": [
          { "ty": "sh", "ks": { "a": 0, "k": { "i": [[0,0],[-4,-3]], "o": [[3,2],[0,0]], "v": [[52,138],[36,150]], "c": false } }, "nm": "B1S1" },
          { "ty": "st", "c": { "a": 0, "k": [0.420, 0.270, 0.130, 1] }, "o": { "a": 0, "k": 100 }, "w": { "a": 0, "k": 2.1 }, "lc": 2, "lj": 2, "nm": "B1S1S" },
          { "ty": "tr", "p": { "a": 0, "k": [0,0] }, "a": { "a": 0, "k": [0,0] }, "s": { "a": 0, "k": [100,100] }, "r": { "a": 0, "k": 0 }, "o": { "a": 0, "k": 100 } }
        ], "nm": "B1S1G" },
        { "ty": "gr", "it": [
          { "ty": "sh", "ks": { "a": 0, "k": { "i": [[0,0],[-2,-1]], "o": [[2,1],[0,0]], "v": [[44,144],[34,154]], "c": false } }, "nm": "B1S1a" },
          { "ty": "st", "c": { "a": 0, "k": [0.380, 0.240, 0.110, 1] }, "o": { "a": 0, "k": 90 }, "w": { "a": 0, "k": 1.4 }, "lc": 2, "lj": 2, "nm": "B1S1aS" },
          { "ty": "tr", "p": { "a": 0, "k": [0,0] }, "a": { "a": 0, "k": [0,0] }, "s": { "a": 0, "k": [100,100] }, "r": { "a": 0, "k": 0 }, "o": { "a": 0, "k": 100 } }
        ], "nm": "B1S1aG" },
        { "ty": "gr", "it": [
          { "ty": "sh", "ks": { "a": 0, "k": { "i": [[0,0],[-3,-2]], "o": [[2,1],[0,0]], "v": [[36,152],[26,160]], "c": false } }, "nm": "B1S2" },
          { "ty": "st", "c": { "a": 0, "k": [0.420, 0.270, 0.130, 1] }, "o": { "a": 0, "k": 100 }, "w": { "a": 0, "k": 1.8 }, "lc": 2, "lj": 2, "nm": "B1S2S" },
          { "ty": "tr", "p": { "a": 0, "k": [0,0] }, "a": { "a": 0, "k": [0,0] }, "s": { "a": 0, "k": [100,100] }, "r": { "a": 0, "k": 0 }, "o": { "a": 0, "k": 100 } }
        ], "nm": "B1S2G" },
        { "ty": "gr", "it": [
          { "ty": "sh", "ks": { "a": 0, "k": { "i": [[0,0],[10,-14]], "o": [[-4,10],[0,0]], "v": [[89,122],[54,192]], "c": false } }, "nm": "B2M" },
          { "ty": "st", "c": { "a": 0, "k": [0.486, 0.314, 0.149, 1] }, "o": { "a": 0, "k": 100 }, "w": { "a": 0, "k": 3.6 }, "lc": 2, "lj": 2, "nm": "B2MS" },
          { "ty": "tr", "p": { "a": 0, "k": [0,0] }, "a": { "a": 0, "k": [0,0] }, "s": { "a": 0, "k": [100,100] }, "r": { "a": 0, "k": 0 }, "o": { "a": 0, "k": 100 } }
        ], "nm": "B2MainG" },
        { "ty": "gr", "it": [
          { "ty": "sh", "ks": { "a": 0, "k": { "i": [[0,0],[-4,1]], "o": [[3,0],[0,0]], "v": [[74,158],[42,178]], "c": false } }, "nm": "B2S1" },
          { "ty": "st", "c": { "a": 0, "k": [0.420, 0.270, 0.130, 1] }, "o": { "a": 0, "k": 100 }, "w": { "a": 0, "k": 2.2 }, "lc": 2, "lj": 2, "nm": "B2S1S" },
          { "ty": "tr", "p": { "a": 0, "k": [0,0] }, "a": { "a": 0, "k": [0,0] }, "s": { "a": 0, "k": [100,100] }, "r": { "a": 0, "k": 0 }, "o": { "a": 0, "k": 100 } }
        ], "nm": "B2S1G" },
        { "ty": "gr", "it": [
          { "ty": "sh", "ks": { "a": 0, "k": { "i": [[0,0],[-2,1]], "o": [[2,-1],[0,0]], "v": [[60,168],[50,182]], "c": false } }, "nm": "B2S1a" },
          { "ty": "st", "c": { "a": 0, "k": [0.380, 0.240, 0.110, 1] }, "o": { "a": 0, "k": 90 }, "w": { "a": 0, "k": 1.4 }, "lc": 2, "lj": 2, "nm": "B2S1aS" },
          { "ty": "tr", "p": { "a": 0, "k": [0,0] }, "a": { "a": 0, "k": [0,0] }, "s": { "a": 0, "k": [100,100] }, "r": { "a": 0, "k": 0 }, "o": { "a": 0, "k": 100 } }
        ], "nm": "B2S1aG" },
        { "ty": "gr", "it": [
          { "ty": "sh", "ks": { "a": 0, "k": { "i": [[0,0],[2,3]], "o": [[-2,-3],[0,0]], "v": [[68,176],[72,188]], "c": false } }, "nm": "B2S2" },
          { "ty": "st", "c": { "a": 0, "k": [0.420, 0.270, 0.130, 1] }, "o": { "a": 0, "k": 100 }, "w": { "a": 0, "k": 1.8 }, "lc": 2, "lj": 2, "nm": "B2S2S" },
          { "ty": "tr", "p": { "a": 0, "k": [0,0] }, "a": { "a": 0, "k": [0,0] }, "s": { "a": 0, "k": [100,100] }, "r": { "a": 0, "k": 0 }, "o": { "a": 0, "k": 100 } }
        ], "nm": "B2S2G" },
        { "ty": "gr", "it": [
          { "ty": "sh", "ks": { "a": 0, "k": { "i": [[0,0],[-2,-14]], "o": [[1,14],[0,0]], "v": [[100,122],[104,195]], "c": false } }, "nm": "B3M" },
          { "ty": "st", "c": { "a": 0, "k": [0.486, 0.314, 0.149, 1] }, "o": { "a": 0, "k": 100 }, "w": { "a": 0, "k": 3.8 }, "lc": 2, "lj": 2, "nm": "B3MS" },
          { "ty": "tr", "p": { "a": 0, "k": [0,0] }, "a": { "a": 0, "k": [0,0] }, "s": { "a": 0, "k": [100,100] }, "r": { "a": 0, "k": 0 }, "o": { "a": 0, "k": 100 } }
        ], "nm": "B3MainG" },
        { "ty": "gr", "it": [
          { "ty": "sh", "ks": { "a": 0, "k": { "i": [[0,0],[3,2]], "o": [[-2,-2],[0,0]], "v": [[102,150],[88,164]], "c": false } }, "nm": "B3S1" },
          { "ty": "st", "c": { "a": 0, "k": [0.420, 0.270, 0.130, 1] }, "o": { "a": 0, "k": 100 }, "w": { "a": 0, "k": 2.1 }, "lc": 2, "lj": 2, "nm": "B3S1S" },
          { "ty": "tr", "p": { "a": 0, "k": [0,0] }, "a": { "a": 0, "k": [0,0] }, "s": { "a": 0, "k": [100,100] }, "r": { "a": 0, "k": 0 }, "o": { "a": 0, "k": 100 } }
        ], "nm": "B3S1G" },
        { "ty": "gr", "it": [
          { "ty": "sh", "ks": { "a": 0, "k": { "i": [[0,0],[2,1]], "o": [[-2,-1],[0,0]], "v": [[95,156],[86,168]], "c": false } }, "nm": "B3S1a" },
          { "ty": "st", "c": { "a": 0, "k": [0.380, 0.240, 0.110, 1] }, "o": { "a": 0, "k": 90 }, "w": { "a": 0, "k": 1.4 }, "lc": 2, "lj": 2, "nm": "B3S1aS" },
          { "ty": "tr", "p": { "a": 0, "k": [0,0] }, "a": { "a": 0, "k": [0,0] }, "s": { "a": 0, "k": [100,100] }, "r": { "a": 0, "k": 0 }, "o": { "a": 0, "k": 100 } }
        ], "nm": "B3S1aG" },
        { "ty": "gr", "it": [
          { "ty": "sh", "ks": { "a": 0, "k": { "i": [[0,0],[-3,2]], "o": [[3,-2],[0,0]], "v": [[103,164],[118,174]], "c": false } }, "nm": "B3S2" },
          { "ty": "st", "c": { "a": 0, "k": [0.420, 0.270, 0.130, 1] }, "o": { "a": 0, "k": 100 }, "w": { "a": 0, "k": 1.9 }, "lc": 2, "lj": 2, "nm": "B3S2S" },
          { "ty": "tr", "p": { "a": 0, "k": [0,0] }, "a": { "a": 0, "k": [0,0] }, "s": { "a": 0, "k": [100,100] }, "r": { "a": 0, "k": 0 }, "o": { "a": 0, "k": 100 } }
        ], "nm": "B3S2G" },
        { "ty": "gr", "it": [
          { "ty": "sh", "ks": { "a": 0, "k": { "i": [[0,0],[-8,-14]], "o": [[3,10],[0,0]], "v": [[111,122],[148,184]], "c": false } }, "nm": "B4M" },
          { "ty": "st", "c": { "a": 0, "k": [0.486, 0.314, 0.149, 1] }, "o": { "a": 0, "k": 100 }, "w": { "a": 0, "k": 3.5 }, "lc": 2, "lj": 2, "nm": "B4MS" },
          { "ty": "tr", "p": { "a": 0, "k": [0,0] }, "a": { "a": 0, "k": [0,0] }, "s": { "a": 0, "k": [100,100] }, "r": { "a": 0, "k": 0 }, "o": { "a": 0, "k": 100 } }
        ], "nm": "B4MainG" },
        { "ty": "gr", "it": [
          { "ty": "sh", "ks": { "a": 0, "k": { "i": [[0,0],[4,0]], "o": [[-3,0],[0,0]], "v": [[128,156],[160,170]], "c": false } }, "nm": "B4S1" },
          { "ty": "st", "c": { "a": 0, "k": [0.420, 0.270, 0.130, 1] }, "o": { "a": 0, "k": 100 }, "w": { "a": 0, "k": 2.2 }, "lc": 2, "lj": 2, "nm": "B4S1S" },
          { "ty": "tr", "p": { "a": 0, "k": [0,0] }, "a": { "a": 0, "k": [0,0] }, "s": { "a": 0, "k": [100,100] }, "r": { "a": 0, "k": 0 }, "o": { "a": 0, "k": 100 } }
        ], "nm": "B4S1G" },
        { "ty": "gr", "it": [
          { "ty": "sh", "ks": { "a": 0, "k": { "i": [[0,0],[2,1]], "o": [[-2,-1],[0,0]], "v": [[142,162],[154,174]], "c": false } }, "nm": "B4S1a" },
          { "ty": "st", "c": { "a": 0, "k": [0.380, 0.240, 0.110, 1] }, "o": { "a": 0, "k": 90 }, "w": { "a": 0, "k": 1.4 }, "lc": 2, "lj": 2, "nm": "B4S1aS" },
          { "ty": "tr", "p": { "a": 0, "k": [0,0] }, "a": { "a": 0, "k": [0,0] }, "s": { "a": 0, "k": [100,100] }, "r": { "a": 0, "k": 0 }, "o": { "a": 0, "k": 100 } }
        ], "nm": "B4S1aG" },
        { "ty": "gr", "it": [
          { "ty": "sh", "ks": { "a": 0, "k": { "i": [[0,0],[3,2]], "o": [[-2,-2],[0,0]], "v": [[136,168],[128,182]], "c": false } }, "nm": "B4S2" },
          { "ty": "st", "c": { "a": 0, "k": [0.420, 0.270, 0.130, 1] }, "o": { "a": 0, "k": 100 }, "w": { "a": 0, "k": 1.8 }, "lc": 2, "lj": 2, "nm": "B4S2S" },
          { "ty": "tr", "p": { "a": 0, "k": [0,0] }, "a": { "a": 0, "k": [0,0] }, "s": { "a": 0, "k": [100,100] }, "r": { "a": 0, "k": 0 }, "o": { "a": 0, "k": 100 } }
        ], "nm": "B4S2G" },
        { "ty": "gr", "it": [
          { "ty": "sh", "ks": { "a": 0, "k": { "i": [[0,0],[-22,-8]], "o": [[14,3],[0,0]], "v": [[120,114],[180,158]], "c": false } }, "nm": "B5M" },
          { "ty": "st", "c": { "a": 0, "k": [0.486, 0.314, 0.149, 1] }, "o": { "a": 0, "k": 100 }, "w": { "a": 0, "k": 3.4 }, "lc": 2, "lj": 2, "nm": "B5MS" },
          { "ty": "tr", "p": { "a": 0, "k": [0,0] }, "a": { "a": 0, "k": [0,0] }, "s": { "a": 0, "k": [100,100] }, "r": { "a": 0, "k": 0 }, "o": { "a": 0, "k": 100 } }
        ], "nm": "B5MainG" },
        { "ty": "gr", "it": [
          { "ty": "sh", "ks": { "a": 0, "k": { "i": [[0,0],[4,2]], "o": [[-3,-2],[0,0]], "v": [[148,136],[170,148]], "c": false } }, "nm": "B5S1" },
          { "ty": "st", "c": { "a": 0, "k": [0.420, 0.270, 0.130, 1] }, "o": { "a": 0, "k": 100 }, "w": { "a": 0, "k": 2.1 }, "lc": 2, "lj": 2, "nm": "B5S1S" },
          { "ty": "tr", "p": { "a": 0, "k": [0,0] }, "a": { "a": 0, "k": [0,0] }, "s": { "a": 0, "k": [100,100] }, "r": { "a": 0, "k": 0 }, "o": { "a": 0, "k": 100 } }
        ], "nm": "B5S1G" },
        { "ty": "gr", "it": [
          { "ty": "sh", "ks": { "a": 0, "k": { "i": [[0,0],[2,1]], "o": [[-2,-1],[0,0]], "v": [[156,141],[166,151]], "c": false } }, "nm": "B5S1a" },
          { "ty": "st", "c": { "a": 0, "k": [0.380, 0.240, 0.110, 1] }, "o": { "a": 0, "k": 90 }, "w": { "a": 0, "k": 1.4 }, "lc": 2, "lj": 2, "nm": "B5S1aS" },
          { "ty": "tr", "p": { "a": 0, "k": [0,0] }, "a": { "a": 0, "k": [0,0] }, "s": { "a": 0, "k": [100,100] }, "r": { "a": 0, "k": 0 }, "o": { "a": 0, "k": 100 } }
        ], "nm": "B5S1aG" },
        { "ty": "gr", "it": [
          { "ty": "sh", "ks": { "a": 0, "k": { "i": [[0,0],[3,2]], "o": [[-3,-2],[0,0]], "v": [[164,146],[174,156]], "c": false } }, "nm": "B5S2" },
          { "ty": "st", "c": { "a": 0, "k": [0.420, 0.270, 0.130, 1] }, "o": { "a": 0, "k": 100 }, "w": { "a": 0, "k": 1.8 }, "lc": 2, "lj": 2, "nm": "B5S2S" },
          { "ty": "tr", "p": { "a": 0, "k": [0,0] }, "a": { "a": 0, "k": [0,0] }, "s": { "a": 0, "k": [100,100] }, "r": { "a": 0, "k": 0 }, "o": { "a": 0, "k": 100 } }
        ], "nm": "B5S2G" }
      ],
      "ip": 0, "op": 120, "st": 0, "bm": 0
    },
    {
      "ddd": 0, "ind": 4, "ty": 4, "nm": "LC1Tip",
      "sr": 1,
      "ks": {
        "o": { "a": 0, "k": 100 }, "r": { "a": 0, "k": 0 },
        "p": { "a": 0, "k": [22, 162, 0] },
        "a": { "a": 0, "k": [0, 0, 0] },
        "s": { "a": 1, "k": [
          { "i": { "x": [0.4, 0.4, 0.4], "y": [1, 1, 1] }, "o": { "x": [0.6, 0.6, 0.6], "y": [0, 0, 0] }, "t": 0, "s": [100, 100, 100] },
          { "i": { "x": [0.4, 0.4, 0.4], "y": [1, 1, 1] }, "o": { "x": [0.6, 0.6, 0.6], "y": [0, 0, 0] }, "t": 60, "s": [106, 96, 100] },
          { "t": 120, "s": [100, 100, 100] }
        ] }
      },
      "shapes": [
        { "ty": "gr", "it": [
          { "ty": "el", "p": { "a": 0, "k": [-10, -4] }, "s": { "a": 0, "k": [20, 16] }, "nm": "L1a" },
          { "ty": "el", "p": { "a": 0, "k": [9, -5] }, "s": { "a": 0, "k": [22, 18] }, "nm": "L1b" },
          { "ty": "el", "p": { "a": 0, "k": [-2, 9] }, "s": { "a": 0, "k": [24, 19] }, "nm": "L1c" },
          { "ty": "fl", "c": { "a": 0, "k": [0.180, 0.490, 0.196, 1] }, "o": { "a": 0, "k": 100 }, "nm": "L1F" },
          { "ty": "st", "c": { "a": 0, "k": [0.106, 0.369, 0.125, 1] }, "o": { "a": 0, "k": 100 }, "w": { "a": 0, "k": 0.8 }, "lc": 2, "lj": 2, "nm": "L1St" },
          { "ty": "tr", "p": { "a": 0, "k": [0, 0] }, "a": { "a": 0, "k": [0, 0] }, "s": { "a": 0, "k": [100, 100] }, "r": { "a": 0, "k": 0 }, "o": { "a": 0, "k": 100 } }
        ], "nm": "LC1TipG" }
      ],
      "ip": 0, "op": 120, "st": 0, "bm": 0
    },
    {
      "ddd": 0, "ind": 5, "ty": 4, "nm": "LC1Mid",
      "sr": 1,
      "ks": {
        "o": { "a": 0, "k": 100 }, "r": { "a": 0, "k": 0 },
        "p": { "a": 0, "k": [52, 138, 0] },
        "a": { "a": 0, "k": [0, 0, 0] },
        "s": { "a": 1, "k": [
          { "i": { "x": [0.4, 0.4, 0.4], "y": [1, 1, 1] }, "o": { "x": [0.6, 0.6, 0.6], "y": [0, 0, 0] }, "t": 0, "s": [102, 98, 100] },
          { "i": { "x": [0.4, 0.4, 0.4], "y": [1, 1, 1] }, "o": { "x": [0.6, 0.6, 0.6], "y": [0, 0, 0] }, "t": 38, "s": [97, 106, 100] },
          { "t": 120, "s": [102, 98, 100] }
        ] }
      },
      "shapes": [
        { "ty": "gr", "it": [
          { "ty": "el", "p": { "a": 0, "k": [-6, -2] }, "s": { "a": 0, "k": [16, 13] }, "nm": "L1Ma" },
          { "ty": "el", "p": { "a": 0, "k": [5, 4] }, "s": { "a": 0, "k": [17, 14] }, "nm": "L1Mb" },
          { "ty": "fl", "c": { "a": 0, "k": [0.180, 0.490, 0.196, 1] }, "o": { "a": 0, "k": 100 }, "nm": "L1MF" },
          { "ty": "st", "c": { "a": 0, "k": [0.106, 0.369, 0.125, 1] }, "o": { "a": 0, "k": 100 }, "w": { "a": 0, "k": 0.8 }, "lc": 2, "lj": 2, "nm": "L1MSt" },
          { "ty": "tr", "p": { "a": 0, "k": [0, 0] }, "a": { "a": 0, "k": [0, 0] }, "s": { "a": 0, "k": [100, 100] }, "r": { "a": 0, "k": 0 }, "o": { "a": 0, "k": 100 } }
        ], "nm": "LC1MidG" }
      ],
      "ip": 0, "op": 120, "st": 0, "bm": 0
    },
    {
      "ddd": 0, "ind": 6, "ty": 4, "nm": "LC1Sub",
      "sr": 1,
      "ks": {
        "o": { "a": 0, "k": 100 }, "r": { "a": 0, "k": 0 },
        "p": { "a": 0, "k": [36, 150, 0] },
        "a": { "a": 0, "k": [0, 0, 0] },
        "s": { "a": 1, "k": [
          { "i": { "x": [0.4, 0.4, 0.4], "y": [1, 1, 1] }, "o": { "x": [0.6, 0.6, 0.6], "y": [0, 0, 0] }, "t": 0, "s": [98, 103, 100] },
          { "i": { "x": [0.4, 0.4, 0.4], "y": [1, 1, 1] }, "o": { "x": [0.6, 0.6, 0.6], "y": [0, 0, 0] }, "t": 45, "s": [104, 96, 100] },
          { "t": 120, "s": [98, 103, 100] }
        ] }
      },
      "shapes": [
        { "ty": "gr", "it": [
          { "ty": "el", "p": { "a": 0, "k": [-5, -2] }, "s": { "a": 0, "k": [15, 12] }, "nm": "L1Sa" },
          { "ty": "el", "p": { "a": 0, "k": [4, 3] }, "s": { "a": 0, "k": [16, 13] }, "nm": "L1Sb" },
          { "ty": "fl", "c": { "a": 0, "k": [0.180, 0.490, 0.196, 1] }, "o": { "a": 0, "k": 100 }, "nm": "L1SF" },
          { "ty": "st", "c": { "a": 0, "k": [0.106, 0.369, 0.125, 1] }, "o": { "a": 0, "k": 100 }, "w": { "a": 0, "k": 0.8 }, "lc": 2, "lj": 2, "nm": "L1SSt" },
          { "ty": "tr", "p": { "a": 0, "k": [0, 0] }, "a": { "a": 0, "k": [0, 0] }, "s": { "a": 0, "k": [100, 100] }, "r": { "a": 0, "k": 0 }, "o": { "a": 0, "k": 100 } }
        ], "nm": "LC1SubG" }
      ],
      "ip": 0, "op": 120, "st": 0, "bm": 0
    },
    {
      "ddd": 0, "ind": 7, "ty": 4, "nm": "LC2Tip",
      "sr": 1,
      "ks": {
        "o": { "a": 0, "k": 100 }, "r": { "a": 0, "k": 0 },
        "p": { "a": 0, "k": [54, 192, 0] },
        "a": { "a": 0, "k": [0, 0, 0] },
        "s": { "a": 1, "k": [
          { "i": { "x": [0.4, 0.4, 0.4], "y": [1, 1, 1] }, "o": { "x": [0.6, 0.6, 0.6], "y": [0, 0, 0] }, "t": 0, "s": [105, 95, 100] },
          { "i": { "x": [0.4, 0.4, 0.4], "y": [1, 1, 1] }, "o": { "x": [0.6, 0.6, 0.6], "y": [0, 0, 0] }, "t": 58, "s": [95, 108, 100] },
          { "t": 120, "s": [105, 95, 100] }
        ] }
      },
      "shapes": [
        { "ty": "gr", "it": [
          { "ty": "el", "p": { "a": 0, "k": [-11, -4] }, "s": { "a": 0, "k": [22, 17] }, "nm": "L2a" },
          { "ty": "el", "p": { "a": 0, "k": [10, -5] }, "s": { "a": 0, "k": [23, 18] }, "nm": "L2b" },
          { "ty": "el", "p": { "a": 0, "k": [0, 8] }, "s": { "a": 0, "k": [25, 19] }, "nm": "L2c" },
          { "ty": "fl", "c": { "a": 0, "k": [0.180, 0.490, 0.196, 1] }, "o": { "a": 0, "k": 100 }, "nm": "L2F" },
          { "ty": "st", "c": { "a": 0, "k": [0.106, 0.369, 0.125, 1] }, "o": { "a": 0, "k": 100 }, "w": { "a": 0, "k": 0.8 }, "lc": 2, "lj": 2, "nm": "L2St" },
          { "ty": "tr", "p": { "a": 0, "k": [0, 0] }, "a": { "a": 0, "k": [0, 0] }, "s": { "a": 0, "k": [100, 100] }, "r": { "a": 0, "k": 0 }, "o": { "a": 0, "k": 100 } }
        ], "nm": "LC2TipG" }
      ],
      "ip": 0, "op": 120, "st": 0, "bm": 0
    },
    {
      "ddd": 0, "ind": 8, "ty": 4, "nm": "LC2Mid",
      "sr": 1,
      "ks": {
        "o": { "a": 0, "k": 100 }, "r": { "a": 0, "k": 0 },
        "p": { "a": 0, "k": [76, 162, 0] },
        "a": { "a": 0, "k": [0, 0, 0] },
        "s": { "a": 1, "k": [
          { "i": { "x": [0.4, 0.4, 0.4], "y": [1, 1, 1] }, "o": { "x": [0.6, 0.6, 0.6], "y": [0, 0, 0] }, "t": 0, "s": [100, 100, 100] },
          { "i": { "x": [0.4, 0.4, 0.4], "y": [1, 1, 1] }, "o": { "x": [0.6, 0.6, 0.6], "y": [0, 0, 0] }, "t": 40, "s": [106, 96, 100] },
          { "t": 120, "s": [100, 100, 100] }
        ] }
      },
      "shapes": [
        { "ty": "gr", "it": [
          { "ty": "el", "p": { "a": 0, "k": [-5, -2] }, "s": { "a": 0, "k": [15, 12] }, "nm": "L2Ma" },
          { "ty": "el", "p": { "a": 0, "k": [4, 4] }, "s": { "a": 0, "k": [16, 13] }, "nm": "L2Mb" },
          { "ty": "fl", "c": { "a": 0, "k": [0.180, 0.490, 0.196, 1] }, "o": { "a": 0, "k": 100 }, "nm": "L2MF" },
          { "ty": "st", "c": { "a": 0, "k": [0.106, 0.369, 0.125, 1] }, "o": { "a": 0, "k": 100 }, "w": { "a": 0, "k": 0.8 }, "lc": 2, "lj": 2, "nm": "L2MSt" },
          { "ty": "tr", "p": { "a": 0, "k": [0, 0] }, "a": { "a": 0, "k": [0, 0] }, "s": { "a": 0, "k": [100, 100] }, "r": { "a": 0, "k": 0 }, "o": { "a": 0, "k": 100 } }
        ], "nm": "LC2MidG" }
      ],
      "ip": 0, "op": 120, "st": 0, "bm": 0
    },
    {
      "ddd": 0, "ind": 9, "ty": 4, "nm": "LC3Tip",
      "sr": 1,
      "ks": {
        "o": { "a": 0, "k": 100 }, "r": { "a": 0, "k": 0 },
        "p": { "a": 0, "k": [104, 195, 0] },
        "a": { "a": 0, "k": [0, 0, 0] },
        "s": { "a": 1, "k": [
          { "i": { "x": [0.4, 0.4, 0.4], "y": [1, 1, 1] }, "o": { "x": [0.6, 0.6, 0.6], "y": [0, 0, 0] }, "t": 0, "s": [98, 104, 100] },
          { "i": { "x": [0.4, 0.4, 0.4], "y": [1, 1, 1] }, "o": { "x": [0.6, 0.6, 0.6], "y": [0, 0, 0] }, "t": 62, "s": [106, 95, 100] },
          { "t": 120, "s": [98, 104, 100] }
        ] }
      },
      "shapes": [
        { "ty": "gr", "it": [
          { "ty": "el", "p": { "a": 0, "k": [-12, -4] }, "s": { "a": 0, "k": [22, 18] }, "nm": "L3a" },
          { "ty": "el", "p": { "a": 0, "k": [11, -4] }, "s": { "a": 0, "k": [22, 17] }, "nm": "L3b" },
          { "ty": "el", "p": { "a": 0, "k": [0, 8] }, "s": { "a": 0, "k": [26, 20] }, "nm": "L3c" },
          { "ty": "fl", "c": { "a": 0, "k": [0.180, 0.490, 0.196, 1] }, "o": { "a": 0, "k": 100 }, "nm": "L3F" },
          { "ty": "st", "c": { "a": 0, "k": [0.106, 0.369, 0.125, 1] }, "o": { "a": 0, "k": 100 }, "w": { "a": 0, "k": 0.8 }, "lc": 2, "lj": 2, "nm": "L3St" },
          { "ty": "tr", "p": { "a": 0, "k": [0, 0] }, "a": { "a": 0, "k": [0, 0] }, "s": { "a": 0, "k": [100, 100] }, "r": { "a": 0, "k": 0 }, "o": { "a": 0, "k": 100 } }
        ], "nm": "LC3TipG" }
      ],
      "ip": 0, "op": 120, "st": 0, "bm": 0
    },
    {
      "ddd": 0, "ind": 10, "ty": 4, "nm": "LC3Sub",
      "sr": 1,
      "ks": {
        "o": { "a": 0, "k": 100 }, "r": { "a": 0, "k": 0 },
        "p": { "a": 0, "k": [118, 168, 0] },
        "a": { "a": 0, "k": [0, 0, 0] },
        "s": { "a": 1, "k": [
          { "i": { "x": [0.4, 0.4, 0.4], "y": [1, 1, 1] }, "o": { "x": [0.6, 0.6, 0.6], "y": [0, 0, 0] }, "t": 0, "s": [100, 100, 100] },
          { "i": { "x": [0.4, 0.4, 0.4], "y": [1, 1, 1] }, "o": { "x": [0.6, 0.6, 0.6], "y": [0, 0, 0] }, "t": 42, "s": [108, 94, 100] },
          { "t": 120, "s": [100, 100, 100] }
        ] }
      },
      "shapes": [
        { "ty": "gr", "it": [
          { "ty": "el", "p": { "a": 0, "k": [-6, -2] }, "s": { "a": 0, "k": [16, 13] }, "nm": "L3Sa" },
          { "ty": "el", "p": { "a": 0, "k": [5, 4] }, "s": { "a": 0, "k": [17, 13] }, "nm": "L3Sb" },
          { "ty": "fl", "c": { "a": 0, "k": [0.180, 0.490, 0.196, 1] }, "o": { "a": 0, "k": 100 }, "nm": "L3SF" },
          { "ty": "st", "c": { "a": 0, "k": [0.106, 0.369, 0.125, 1] }, "o": { "a": 0, "k": 100 }, "w": { "a": 0, "k": 0.8 }, "lc": 2, "lj": 2, "nm": "L3SSt" },
          { "ty": "tr", "p": { "a": 0, "k": [0, 0] }, "a": { "a": 0, "k": [0, 0] }, "s": { "a": 0, "k": [100, 100] }, "r": { "a": 0, "k": 0 }, "o": { "a": 0, "k": 100 } }
        ], "nm": "LC3SubG" }
      ],
      "ip": 0, "op": 120, "st": 0, "bm": 0
    },
    {
      "ddd": 0, "ind": 11, "ty": 4, "nm": "LC4Tip",
      "sr": 1,
      "ks": {
        "o": { "a": 0, "k": 100 }, "r": { "a": 0, "k": 0 },
        "p": { "a": 0, "k": [148, 184, 0] },
        "a": { "a": 0, "k": [0, 0, 0] },
        "s": { "a": 1, "k": [
          { "i": { "x": [0.4, 0.4, 0.4], "y": [1, 1, 1] }, "o": { "x": [0.6, 0.6, 0.6], "y": [0, 0, 0] }, "t": 0, "s": [103, 96, 100] },
          { "i": { "x": [0.4, 0.4, 0.4], "y": [1, 1, 1] }, "o": { "x": [0.6, 0.6, 0.6], "y": [0, 0, 0] }, "t": 65, "s": [107, 96, 100] },
          { "t": 120, "s": [103, 96, 100] }
        ] }
      },
      "shapes": [
        { "ty": "gr", "it": [
          { "ty": "el", "p": { "a": 0, "k": [-10, -4] }, "s": { "a": 0, "k": [21, 17] }, "nm": "L4a" },
          { "ty": "el", "p": { "a": 0, "k": [11, -3] }, "s": { "a": 0, "k": [20, 17] }, "nm": "L4b" },
          { "ty": "el", "p": { "a": 0, "k": [1, 9] }, "s": { "a": 0, "k": [24, 19] }, "nm": "L4c" },
          { "ty": "fl", "c": { "a": 0, "k": [0.180, 0.490, 0.196, 1] }, "o": { "a": 0, "k": 100 }, "nm": "L4F" },
          { "ty": "st", "c": { "a": 0, "k": [0.106, 0.369, 0.125, 1] }, "o": { "a": 0, "k": 100 }, "w": { "a": 0, "k": 0.8 }, "lc": 2, "lj": 2, "nm": "L4St" },
          { "ty": "tr", "p": { "a": 0, "k": [0, 0] }, "a": { "a": 0, "k": [0, 0] }, "s": { "a": 0, "k": [100, 100] }, "r": { "a": 0, "k": 0 }, "o": { "a": 0, "k": 100 } }
        ], "nm": "LC4TipG" }
      ],
      "ip": 0, "op": 120, "st": 0, "bm": 0
    },
    {
      "ddd": 0, "ind": 12, "ty": 4, "nm": "LC4Mid",
      "sr": 1,
      "ks": {
        "o": { "a": 0, "k": 100 }, "r": { "a": 0, "k": 0 },
        "p": { "a": 0, "k": [128, 156, 0] },
        "a": { "a": 0, "k": [0, 0, 0] },
        "s": { "a": 1, "k": [
          { "i": { "x": [0.4, 0.4, 0.4], "y": [1, 1, 1] }, "o": { "x": [0.6, 0.6, 0.6], "y": [0, 0, 0] }, "t": 0, "s": [98, 102, 100] },
          { "i": { "x": [0.4, 0.4, 0.4], "y": [1, 1, 1] }, "o": { "x": [0.6, 0.6, 0.6], "y": [0, 0, 0] }, "t": 48, "s": [105, 95, 100] },
          { "t": 120, "s": [98, 102, 100] }
        ] }
      },
      "shapes": [
        { "ty": "gr", "it": [
          { "ty": "el", "p": { "a": 0, "k": [-5, -3] }, "s": { "a": 0, "k": [16, 13] }, "nm": "L4Ma" },
          { "ty": "el", "p": { "a": 0, "k": [5, 4] }, "s": { "a": 0, "k": [17, 14] }, "nm": "L4Mb" },
          { "ty": "fl", "c": { "a": 0, "k": [0.180, 0.490, 0.196, 1] }, "o": { "a": 0, "k": 100 }, "nm": "L4MF" },
          { "ty": "st", "c": { "a": 0, "k": [0.106, 0.369, 0.125, 1] }, "o": { "a": 0, "k": 100 }, "w": { "a": 0, "k": 0.8 }, "lc": 2, "lj": 2, "nm": "L4MSt" },
          { "ty": "tr", "p": { "a": 0, "k": [0, 0] }, "a": { "a": 0, "k": [0, 0] }, "s": { "a": 0, "k": [100, 100] }, "r": { "a": 0, "k": 0 }, "o": { "a": 0, "k": 100 } }
        ], "nm": "LC4MidG" }
      ],
      "ip": 0, "op": 120, "st": 0, "bm": 0
    },
    {
      "ddd": 0, "ind": 13, "ty": 4, "nm": "LC4Sub",
      "sr": 1,
      "ks": {
        "o": { "a": 0, "k": 100 }, "r": { "a": 0, "k": 0 },
        "p": { "a": 0, "k": [160, 170, 0] },
        "a": { "a": 0, "k": [0, 0, 0] },
        "s": { "a": 1, "k": [
          { "i": { "x": [0.4, 0.4, 0.4], "y": [1, 1, 1] }, "o": { "x": [0.6, 0.6, 0.6], "y": [0, 0, 0] }, "t": 0, "s": [102, 99, 100] },
          { "i": { "x": [0.4, 0.4, 0.4], "y": [1, 1, 1] }, "o": { "x": [0.6, 0.6, 0.6], "y": [0, 0, 0] }, "t": 55, "s": [96, 106, 100] },
          { "t": 120, "s": [102, 99, 100] }
        ] }
      },
      "shapes": [
        { "ty": "gr", "it": [
          { "ty": "el", "p": { "a": 0, "k": [-6, -3] }, "s": { "a": 0, "k": [17, 14] }, "nm": "L4Sa" },
          { "ty": "el", "p": { "a": 0, "k": [5, 3] }, "s": { "a": 0, "k": [18, 14] }, "nm": "L4Sb" },
          { "ty": "fl", "c": { "a": 0, "k": [0.180, 0.490, 0.196, 1] }, "o": { "a": 0, "k": 100 }, "nm": "L4SF" },
          { "ty": "st", "c": { "a": 0, "k": [0.106, 0.369, 0.125, 1] }, "o": { "a": 0, "k": 100 }, "w": { "a": 0, "k": 0.8 }, "lc": 2, "lj": 2, "nm": "L4SSt" },
          { "ty": "tr", "p": { "a": 0, "k": [0, 0] }, "a": { "a": 0, "k": [0, 0] }, "s": { "a": 0, "k": [100, 100] }, "r": { "a": 0, "k": 0 }, "o": { "a": 0, "k": 100 } }
        ], "nm": "LC4SubG" }
      ],
      "ip": 0, "op": 120, "st": 0, "bm": 0
    },
    {
      "ddd": 0, "ind": 14, "ty": 4, "nm": "LC5Tip",
      "sr": 1,
      "ks": {
        "o": { "a": 0, "k": 100 }, "r": { "a": 0, "k": 0 },
        "p": { "a": 0, "k": [180, 158, 0] },
        "a": { "a": 0, "k": [0, 0, 0] },
        "s": { "a": 1, "k": [
          { "i": { "x": [0.4, 0.4, 0.4], "y": [1, 1, 1] }, "o": { "x": [0.6, 0.6, 0.6], "y": [0, 0, 0] }, "t": 0, "s": [96, 105, 100] },
          { "i": { "x": [0.4, 0.4, 0.4], "y": [1, 1, 1] }, "o": { "x": [0.6, 0.6, 0.6], "y": [0, 0, 0] }, "t": 56, "s": [108, 95, 100] },
          { "t": 120, "s": [96, 105, 100] }
        ] }
      },
      "shapes": [
        { "ty": "gr", "it": [
          { "ty": "el", "p": { "a": 0, "k": [-10, -4] }, "s": { "a": 0, "k": [20, 16] }, "nm": "L5a" },
          { "ty": "el", "p": { "a": 0, "k": [9, -5] }, "s": { "a": 0, "k": [22, 18] }, "nm": "L5b" },
          { "ty": "el", "p": { "a": 0, "k": [-1, 9] }, "s": { "a": 0, "k": [23, 18] }, "nm": "L5c" },
          { "ty": "fl", "c": { "a": 0, "k": [0.180, 0.490, 0.196, 1] }, "o": { "a": 0, "k": 100 }, "nm": "L5F" },
          { "ty": "st", "c": { "a": 0, "k": [0.106, 0.369, 0.125, 1] }, "o": { "a": 0, "k": 100 }, "w": { "a": 0, "k": 0.8 }, "lc": 2, "lj": 2, "nm": "L5St" },
          { "ty": "tr", "p": { "a": 0, "k": [0, 0] }, "a": { "a": 0, "k": [0, 0] }, "s": { "a": 0, "k": [100, 100] }, "r": { "a": 0, "k": 0 }, "o": { "a": 0, "k": 100 } }
        ], "nm": "LC5TipG" }
      ],
      "ip": 0, "op": 120, "st": 0, "bm": 0
    },
    {
      "ddd": 0, "ind": 15, "ty": 4, "nm": "LC5Mid",
      "sr": 1,
      "ks": {
        "o": { "a": 0, "k": 100 }, "r": { "a": 0, "k": 0 },
        "p": { "a": 0, "k": [152, 138, 0] },
        "a": { "a": 0, "k": [0, 0, 0] },
        "s": { "a": 1, "k": [
          { "i": { "x": [0.4, 0.4, 0.4], "y": [1, 1, 1] }, "o": { "x": [0.6, 0.6, 0.6], "y": [0, 0, 0] }, "t": 0, "s": [100, 100, 100] },
          { "i": { "x": [0.4, 0.4, 0.4], "y": [1, 1, 1] }, "o": { "x": [0.6, 0.6, 0.6], "y": [0, 0, 0] }, "t": 50, "s": [106, 95, 100] },
          { "t": 120, "s": [100, 100, 100] }
        ] }
      },
      "shapes": [
        { "ty": "gr", "it": [
          { "ty": "el", "p": { "a": 0, "k": [-5, -2] }, "s": { "a": 0, "k": [16, 13] }, "nm": "L5Ma" },
          { "ty": "el", "p": { "a": 0, "k": [4, 4] }, "s": { "a": 0, "k": [17, 14] }, "nm": "L5Mb" },
          { "ty": "fl", "c": { "a": 0, "k": [0.180, 0.490, 0.196, 1] }, "o": { "a": 0, "k": 100 }, "nm": "L5MF" },
          { "ty": "st", "c": { "a": 0, "k": [0.106, 0.369, 0.125, 1] }, "o": { "a": 0, "k": 100 }, "w": { "a": 0, "k": 0.8 }, "lc": 2, "lj": 2, "nm": "L5MSt" },
          { "ty": "tr", "p": { "a": 0, "k": [0, 0] }, "a": { "a": 0, "k": [0, 0] }, "s": { "a": 0, "k": [100, 100] }, "r": { "a": 0, "k": 0 }, "o": { "a": 0, "k": 100 } }
        ], "nm": "LC5MidG" }
      ],
      "ip": 0, "op": 120, "st": 0, "bm": 0
    }
  ],
  "markers": []
}
